mediqbox/md2pptx/__init__.py
mediqbox/md2pptx/martin/card.py
mediqbox/md2pptx/martin/colour.py
mediqbox/md2pptx/martin/funnel.py
mediqbox/md2pptx/martin/md2pptx.py
mediqbox/md2pptx/martin/rectangle.py
mediqbox/md2pptx/martin/run_pyto.py
mediqbox/md2pptx/martin/symbols.py
mediqbox_md2pptx-0.0.7.dist-info/LICENSE
mediqbox_md2pptx-0.0.7.dist-info/METADATA
mediqbox_md2pptx-0.0.7.dist-info/WHEEL
mediqbox_md2pptx-0.0.7.dist-info/top_level.txt
mediqbox_md2pptx-0.0.7.dist-info/RECORD
